ltlcross_runner/__init__.py
ltlcross_runner/experiments_lib.py
ltlcross_runner/locate_errors.py
ltlcross_runner/ltlcross_runner.py
ltlcross_runner/modular.py
ltlcross_runner/tables_utils.py
ltlcross_runner-0.3.dist-info/LICENSE
ltlcross_runner-0.3.dist-info/METADATA
ltlcross_runner-0.3.dist-info/WHEEL
ltlcross_runner-0.3.dist-info/top_level.txt
ltlcross_runner-0.3.dist-info/RECORD
